studiolab_ml/__init__.py
studiolab_ml/common.py
studiolab_ml/fic.py
studiolab_ml/mlft.py
studiolab_ml/posecompo.py
studiolab_ml/fic_utils/__init__.py
studiolab_ml/fic_utils/meta.py
studiolab_ml/fic_utils/postprocess.py
studiolab_ml/fic_utils/preprocess.py
studiolab_ml/fic_utils/token.py
studiolab_ml/fic_utils/src/mlft_kor.csv
studiolab_ml/fic_utils/src/rules.yaml
studiolab_ml/mlft_utils/__init__.py
studiolab_ml/mlft_utils/bbox.py
studiolab_ml/mlft_utils/det_postprocess.py
studiolab_ml/mlft_utils/det_preprocess.py
studiolab_ml/mlft_utils/filters.py
studiolab_ml/mlft_utils/meta.py
studiolab_ml/mlft_utils/mlft_attr.py
studiolab_ml/mlft_utils/nick_name.py
studiolab_ml/mlft_utils/nicknames_dress.csv
studiolab_ml/mlft_utils/nicknames_outer.csv
studiolab_ml/mlft_utils/nicknames_pants.csv
studiolab_ml/mlft_utils/nicknames_skirt.csv
studiolab_ml/mlft_utils/nicknames_top.csv
studiolab_ml/mlft_utils/src/nicknames_dress.csv
studiolab_ml/mlft_utils/src/nicknames_outer.csv
studiolab_ml/mlft_utils/src/nicknames_pants.csv
studiolab_ml/mlft_utils/src/nicknames_skirt.csv
studiolab_ml/mlft_utils/src/nicknames_top.csv
studiolab_ml-0.1.1.dist-info/LICENSE
studiolab_ml-0.1.1.dist-info/METADATA
studiolab_ml-0.1.1.dist-info/WHEEL
studiolab_ml-0.1.1.dist-info/top_level.txt
studiolab_ml-0.1.1.dist-info/RECORD
